{
  "slug": "core_drill",
  "built_on": "2026-05-11",
  "origin": "synthesis",
  "idea": {
    "title": "Core Drill",
    "title_ru": "Бур Артефакта",
    "hook": "Drill core samples through soil tiles to fully reveal the daily buried artefact before charges run out.",
    "prototype": "12x12 top-down grid of 3-depth tiles. Click drills one chunk. Tile-weight icon telegraphs contents. Daily seed picks the buried artefact silhouette (axe/urn/skull/coin). Win at 80% revealed, lose at 0 charges.",
    "mutation_of": "Glacier Splitter / Frost Crack (chunk-destruction)",
    "why_novel": "Layered depth + daily-seed silhouette reveal differs from surface crack-propagation. Charge budget gives turn-based pacing without a clock.",
    "non_timer_pressure": "Limited drill charges (turn budget, START_CHARGES=40)",
    "lose_condition": "Drill charges hit zero before silhouette reveal reaches 80%"
  },
  "sources": [
    {"source":"telegram","section":"nobice","title":"procedural chunk destruction","url":"https://t.me/nobice/2348","snippet":"Chunk-destruction VFX feels great even with simple shape primitives; pair it with reveal mechanics."},
    {"source":"telegram","section":"nobice","title":"reveal-loop satisfaction","url":"https://t.me/nobice/2347","snippet":"Player-driven reveal beats automatic timers — agency on every click."},
    {"source":"telegram","section":"indiealesha","title":"daily-seed artefact theme","url":"https://t.me/indiealesha/1695","snippet":"Daily-seed mystery themes give universal hook without language overhead."}
  ],
  "synthesizer_brief": "Chunk-destruction reveal with daily-seed artefact silhouette; charges budget for non-timer pacing",
  "alternatives": [
    {"title":"Glyph Lock","title_ru":"Глифокод","hook":"Decode today's emoji-rebus phrase in three guesses","mutation_of":"Wordle","why_novel":"Language-neutral emoji-rebus daily puzzle"},
    {"title":"Varnish Restore","title_ru":"Реставратор","hook":"Rub varnish off a daily oil painting","mutation_of":"Clean Sweep","why_novel":"Drag-rub with chip-budget restraint"},
    {"title":"Window Watch","title_ru":"Соседи","hook":"Spot the odd tenant in apartment grid","mutation_of":"Apartment Cleaner","why_novel":"Observation/spot-the-difference vs cleaning"},
    {"title":"Seawall Stand","title_ru":"Волнорез","hook":"Stack boulders against waves","mutation_of":"Tower Defense","why_novel":"Wave-erosion tile destruction"}
  ]
}
